saveddit/__init__.py
saveddit/_version.py
saveddit/configuration.py
saveddit/multireddit_downloader.py
saveddit/multireddit_downloader_config.py
saveddit/saveddit.py
saveddit/search_config.py
saveddit/search_subreddits.py
saveddit/submission_downloader.py
saveddit/subreddit_downloader.py
saveddit/subreddit_downloader_config.py
saveddit/user_downloader.py
saveddit/user_downloader_config.py
saveddit-2.2.1.dist-info/LICENSE
saveddit-2.2.1.dist-info/METADATA
saveddit-2.2.1.dist-info/WHEEL
saveddit-2.2.1.dist-info/entry_points.txt
saveddit-2.2.1.dist-info/top_level.txt
saveddit-2.2.1.dist-info/RECORD
