Metadata-Version: 2.1
Name: saveddit
Version: 2.2.1
Summary: Bulk Downloader for Reddit
Home-page: https://github.com/p-ranav/saveddit
Author: Pranav Srinivas Kumar
Author-email: pranav.srinivas.kumar@gmail.com
License: UNKNOWN
Project-URL: Bug Tracker, https://github.com/p-ranav/saveddit/issues
Platform: UNKNOWN
Classifier: Programming Language :: Python :: 3
Classifier: License :: OSI Approved :: MIT License
Classifier: Operating System :: OS Independent
Requires-Python: >=3.8
Requires-Dist: praw
Requires-Dist: verboselogs
Requires-Dist: requests
Requires-Dist: colorama
Requires-Dist: coloredlogs
Requires-Dist: youtube-dl
Requires-Dist: tqdm
Requires-Dist: ffmpeg-python
Requires-Dist: beautifulsoup4
Requires-Dist: PyYAML
